odoo/addons/hr_worked_days_from_timesheet/README.rst
odoo/addons/hr_worked_days_from_timesheet/__init__.py
odoo/addons/hr_worked_days_from_timesheet/__manifest__.py
odoo/addons/hr_worked_days_from_timesheet/i18n/cs_CZ.po
odoo/addons/hr_worked_days_from_timesheet/i18n/de.po
odoo/addons/hr_worked_days_from_timesheet/i18n/es.po
odoo/addons/hr_worked_days_from_timesheet/i18n/fr.po
odoo/addons/hr_worked_days_from_timesheet/i18n/hr_worked_days_from_timesheet.pot
odoo/addons/hr_worked_days_from_timesheet/i18n/it.po
odoo/addons/hr_worked_days_from_timesheet/i18n/sl.po
odoo/addons/hr_worked_days_from_timesheet/models/__init__.py
odoo/addons/hr_worked_days_from_timesheet/models/hr_payslip.py
odoo/addons/hr_worked_days_from_timesheet/models/hr_payslip_worked_days.py
odoo/addons/hr_worked_days_from_timesheet/readme/CONTRIBUTORS.rst
odoo/addons/hr_worked_days_from_timesheet/readme/DESCRIPTION.rst
odoo/addons/hr_worked_days_from_timesheet/readme/USAGE.rst
odoo/addons/hr_worked_days_from_timesheet/static/description/icon.png
odoo/addons/hr_worked_days_from_timesheet/static/description/index.html
odoo/addons/hr_worked_days_from_timesheet/tests/__init__.py
odoo/addons/hr_worked_days_from_timesheet/tests/test_worked_days_from_timesheet.py
odoo/addons/hr_worked_days_from_timesheet/views/hr_payslip_view.xml
odoo_addon_hr_worked_days_from_timesheet-15.0.1.0.0.7.dist-info/METADATA
odoo_addon_hr_worked_days_from_timesheet-15.0.1.0.0.7.dist-info/WHEEL
odoo_addon_hr_worked_days_from_timesheet-15.0.1.0.0.7.dist-info/top_level.txt
odoo_addon_hr_worked_days_from_timesheet-15.0.1.0.0.7.dist-info/RECORD
