Metadata-Version: 2.1
Name: odoo-addon-hr-worked-days-from-timesheet
Version: 15.0.1.0.0.7
Summary: Adds a button to import worked days from timesheet.
Home-page: https://github.com/OCA/hr
Author: Savoir-faire Linux, Acysos S.L., ForgeFlow, Serpent Consulting Services Pvt. Ltd.,Odoo Community Association (OCA)
Author-email: support@odoo-community.org
License: AGPL-3
Platform: UNKNOWN
Classifier: Programming Language :: Python
Classifier: Framework :: Odoo
Classifier: Framework :: Odoo :: 15.0
Classifier: License :: OSI Approved :: GNU Affero General Public License v3
Requires-Python: >=3.8
Requires-Dist: odoo-addon-hr-timesheet-sheet <15.1dev,>=15.0dev
Requires-Dist: odoo-addon-payroll <15.1dev,>=15.0dev
Requires-Dist: odoo <15.1dev,>=15.0a
